[
  {
    "log_likelihood": -27.243494987487793,
    "avg_log_likelihood": -2.7243494987487793,
    "perplexity": 15.246492837700893,
    "vocab": [
      "A",
      "C",
      "D",
      "E",
      "F",
      "G",
      "H",
      "I",
      "K",
      "L",
      "M",
      "N",
      "P",
      "Q",
      "R",
      "S",
      "T",
      "V",
      "W",
      "Y"
    ]
  },
  {
    "log_likelihood": -28.39646053314209,
    "avg_log_likelihood": -2.839646053314209,
    "perplexity": 17.109708540649383,
    "vocab": [
      "A",
      "C",
      "D",
      "E",
      "F",
      "G",
      "H",
      "I",
      "K",
      "L",
      "M",
      "N",
      "P",
      "Q",
      "R",
      "S",
      "T",
      "V",
      "W",
      "Y"
    ]
  }
]